findhelp/__main__.py
findhelp/config.yaml
findhelp/custom_exceptions.py
findhelp/custom_utils.py
findhelp/finder.py
findhelp-0.1.1.dist-info/LICENSE.txt
findhelp-0.1.1.dist-info/METADATA
findhelp-0.1.1.dist-info/WHEEL
findhelp-0.1.1.dist-info/top_level.txt
findhelp-0.1.1.dist-info/RECORD
