Metadata-Version: 2.1
Name: findhelp
Version: 0.1.1
Summary: Helps finding files / directories using custom parameters
Home-page: https://github.com/rendongarcia/findhelp
Author: Miguel Ángel Rendón García
Author-email: miguerendongarcia@gmail.com
License: UNKNOWN
Keywords: find,search,file,folder
Platform: UNKNOWN
Classifier: Development Status :: 3 - Alpha
Classifier: Intended Audience :: Developers
Classifier: Intended Audience :: Science/Research
Classifier: Intended Audience :: Education
Classifier: License :: OSI Approved :: MIT License
Classifier: Natural Language :: English
Classifier: Operating System :: OS Independent
Classifier: Programming Language :: Python
Classifier: Programming Language :: Python :: 3
Classifier: Programming Language :: Python :: 3.7
Classifier: Topic :: Education
Requires-Python: >=3.7
License-File: LICENSE.txt
Requires-Dist: PyYaml
Requires-Dist: pandas (>=1.0.0)
Requires-Dist: Unidecode (>=1.0.22)
